chess/__init__.py
chess/criterion.py
chess/datasets.py
chess/manifold.py
chess/types.py
CHESS_python-2.0.0.dist-info/LICENSE
CHESS_python-2.0.0.dist-info/METADATA
CHESS_python-2.0.0.dist-info/WHEEL
CHESS_python-2.0.0.dist-info/top_level.txt
CHESS_python-2.0.0.dist-info/RECORD
