Metadata-Version: 2.1
Name: CHESS-python
Version: 2.0.0
Summary: Clustered Hierarchical Entropy-Scaling Search
Home-page: https://github.com/nishaq503/CHESS
Author: Najib Ishaq, Thomas Howard III
Author-email: 
License: UNKNOWN
Platform: UNKNOWN
Requires-Python: >=3.6
Requires-Dist: numpy
Requires-Dist: scipy
